cbm/__init__.py
cbm/card2db/__init__.py
cbm/card2db/creodias.py
cbm/datas/__init__.py
cbm/datas/api.py
cbm/datas/db.py
cbm/datas/db_queries.py
cbm/datas/direct.py
cbm/datas/image_requests.py
cbm/datas/object_storage.py
cbm/extract/__init__.py
cbm/extract/db_tables.py
cbm/extract/pgS1bsExtract.py
cbm/extract/pgS2Extract.py
cbm/foi/__init__.py
cbm/foi/foi_v1.py
cbm/foi/foi_v2.py
cbm/foi/foi_db_func/checkCardinality.func
cbm/foi/foi_db_func/checkHeterogeneity.func
cbm/get/__init__.py
cbm/get/background.py
cbm/get/chip_images.py
cbm/get/parcel_info.py
cbm/get/parcels_list.py
cbm/get/time_series.py
cbm/ipycbm/__init__.py
cbm/ipycbm/ipy_ext/__init__.py
cbm/ipycbm/ipy_ext/ext_card2db.py
cbm/ipycbm/ipy_ext/ext_func.py
cbm/ipycbm/ipy_ext/ext_main.py
cbm/ipycbm/ipy_ext/ext_panel.py
cbm/ipycbm/ipy_ext/dias/__init__.py
cbm/ipycbm/ipy_ext/dias/creodias.py
cbm/ipycbm/ipy_foi/__init__.py
cbm/ipycbm/ipy_foi/foi_help.py
cbm/ipycbm/ipy_foi/foi_main.py
cbm/ipycbm/ipy_foi/foi_panel.py
cbm/ipycbm/ipy_get/__init__.py
cbm/ipycbm/ipy_get/get_main.py
cbm/ipycbm/ipy_get/get_maps.py
cbm/ipycbm/ipy_get/get_panel.py
cbm/ipycbm/ipy_qa/__init__.py
cbm/ipycbm/ipy_qa/qa_main.py
cbm/ipycbm/ipy_qa/qa_panel.py
cbm/ipycbm/ipy_view/__init__.py
cbm/ipycbm/ipy_view/view_background.py
cbm/ipycbm/ipy_view/view_grid.py
cbm/ipycbm/ipy_view/view_info.py
cbm/ipycbm/ipy_view/view_main.py
cbm/ipycbm/ipy_view/view_map.py
cbm/ipycbm/ipy_view/view_notes.py
cbm/ipycbm/ipy_view/view_panel.py
cbm/ipycbm/ipy_view/view_time_series.py
cbm/ipycbm/utils/__init__.py
cbm/ipycbm/utils/cbm_widgets.py
cbm/ipycbm/utils/help_docs.py
cbm/ipycbm/utils/settings.py
cbm/ipycbm/utils/settings_ds.py
cbm/reports/__init__.py
cbm/reports/export_to_pdf.py
cbm/show/__init__.py
cbm/show/background.py
cbm/show/chip_images.py
cbm/show/parcel_info.py
cbm/show/time_series.py
cbm/utils/__init__.py
cbm/utils/config.py
cbm/utils/data_options.py
cbm/utils/init.py
cbm/utils/raster_utils.py
cbm/utils/update.py
cbm/utils/default/api_options.json
cbm-0.0.18.dist-info/LICENSE
cbm-0.0.18.dist-info/METADATA
cbm-0.0.18.dist-info/WHEEL
cbm-0.0.18.dist-info/top_level.txt
cbm-0.0.18.dist-info/RECORD
