Metadata-Version: 2.1
Name: cbm
Version: 0.0.18
Summary: Checks by Monitoring (CbM)
Home-page: https://github.com/ec-jrc/cbm
Author: Guido Lemoine, Konstantinos Anastasakis
Author-email: 
License: BSD 3-clause
Classifier: Development Status :: 3 - Alpha
Classifier: Intended Audience :: Science/Research
Classifier: License :: OSI Approved :: BSD License
Classifier: Operating System :: POSIX :: Linux
Classifier: Programming Language :: Python :: 3.6
Requires-Python: >=3.6
License-File: LICENSE
Requires-Dist: numpy (>=1.21)
Requires-Dist: matplotlib (>=3.3.0)
Requires-Dist: pandas (>=1.1.0)
Requires-Dist: rasterio (>=1.1.5)
Requires-Dist: requests (>=2.24.0)
Requires-Dist: descartes (>=1.1.0)
Requires-Dist: scikit-image (>=0.19.0)
Requires-Dist: psycopg2-binary
